colab_cli/__init__.py
colab_cli/cli_new.py
colab_cli/cli_open.py
colab_cli/cli_pull.py
colab_cli/cli_push.py
colab_cli/gdrive_auth.py
colab_cli/main.py
colab_cli/utilities/__init__.py
colab_cli/utilities/checks.py
colab_cli/utilities/colab_metadata.py
colab_cli/utilities/files.py
colab_cli/utilities/folders.py
colab_cli/utilities/fun.py
colab_cli/utilities/git_root.py
colab_cli/utilities/path_process.py
colab_cli-2.2.5.dist-info/entry_points.txt
colab_cli-2.2.5.dist-info/LICENSE
colab_cli-2.2.5.dist-info/WHEEL
colab_cli-2.2.5.dist-info/METADATA
colab_cli-2.2.5.dist-info/RECORD
