Metadata-Version: 2.1
Name: colab-cli
Version: 2.2.5
Summary: Experience better workflow with google colab, local jupyter notebooks and git
Home-page: https://github.com/Akshay090/colab-cli
License: MIT
Author: Akshay Ashok
Author-email: aks28id@gmail.com
Requires-Python: >=3.7,<4.0
Classifier: License :: OSI Approved :: MIT License
Classifier: Programming Language :: Python :: 3
Classifier: Programming Language :: Python :: 3.7
Classifier: Programming Language :: Python :: 3.8
Requires-Dist: Send2Trash (>=1.5.0,<2.0.0)
Requires-Dist: colorama (>=0.4.3,<0.5.0)
Requires-Dist: pydrive (>=1.3.1,<2.0.0)
Requires-Dist: typer[all] (>=0.1.0,<0.2.0)
Project-URL: Repository, https://github.com/Akshay090/colab-cli
